[
  {
    "id": "arbeitslosenquote",
    "unit": "%",
    "factor": 1,
    "max": 20,
    "precision": 10,
    "breakpoint": 2005,
    "values": [
      { "year": 2002, "value": 8.6 },
      { "year": 2003, "value": 9.7 },
      { "year": 2004, "value": 10.4 },
      { "year": 2005, "value": 11.2 },
      { "year": 2006, "value": 10.1 },
      { "year": 2007, "value": 8.5 },
      { "year": 2008, "value": 7.4 },
      { "year": 2009, "value": 7.6 },
      { "year": 2010, "value": 7.0 },
      { "year": 2011, "value": 5.8 },
      { "year": 2012, "value": 5.4 },
      { "year": 2013, "value": 5.2 },
      { "year": 2014, "value": 5.0 },
      { "year": 2015, "value": 4.6 },
      { "year": 2016, "value": 4.1 }
    ],
    "annotations": []
  }, {
    "id": "hartz4-kinder",
    "unit": "Mio.",
    "factor": 1000000,
    "max": 4000000,
    "precision": 100,
    "breakpoint": 2005,
    "values": [
      { "year": 2004, "value": 1621094 },
      { "year": 2005, "value": 2150469 },
      { "year": 2006, "value": 2244899 },
      { "year": 2007, "value": 2189021 },
      { "year": 2008, "value": 2048649 },
      { "year": 2009, "value": 2060822 },
      { "year": 2010, "value": 1973214 },
      { "year": 2011, "value": 1879300 },
      { "year": 2012, "value": 1866783 },
      { "year": 2013, "value": 1886472 },
      { "year": 2014, "value": 1906330 },
      { "year": 2015, "value": 1931474 }
    ],
    "annotations": []
  }, {
    "id": "superreiche",
    "unit": "Mrd. $",
    "factor": 1,
    "max": 200,
    "precision": 10,
    "breakpoint": 2005,
    "values": [
      {"year": 2002,"value": 85.1},
      {"year": 2003,"value": 71.4},
      {"year": 2004,"value": 95.8},
      {"year": 2005,"value": 91.6},
      {"year": 2006,"value": 98.1},
      {"year": 2007,"value": 113.6},
      {"year": 2008,"value": 132.5},
      {"year": 2009,"value": 97},
      {"year": 2010,"value": 106.6},
      {"year": 2011,"value": 126.7},
      {"year": 2012,"value": 126.4},
      {"year": 2013,"value": 141.5},
      {"year": 2014,"value": 162.4},
      {"year": 2015,"value": 172},
      {"year": 2016,"value": 161.4},
      {"year": 2017,"value": 170.1}
    ],
    "annotations": []
  }, {
    "id": "staatsverschuldung",
    "unit": "Bio. €",
    "factor": 1000000,
    "max": 2500000,
    "precision": 100,
    "breakpoint": 2005,
    "values": [
      { "year": 2002, "value": 1277271 },
      { "year": 2003, "value": 1357723 },
      { "year": 2004, "value": 1429749 },
      { "year": 2005, "value": 1489852 },
      { "year": 2006, "value": 1545364 },
      { "year": 2007, "value": 1552371 },
      { "year": 2008, "value": 1577881 },
      { "year": 2009, "value": 1694368 },
      { "year": 2010, "value": 2011677 },
      { "year": 2011, "value": 2025438 },
      { "year": 2012, "value": 2068289 },
      { "year": 2013, "value": 2043344 },
      { "year": 2014, "value": 2043918 },
      { "year": 2015, "value": 2022562 }
    ],
    "annotations": []
  }, {
    "id": "soldaten",
    "unit": "Tsd.",
    "factor": 1000,
    "max": 40000,
    "precision": 10,
    "breakpoint": 2005,
    "values": [
      { "year": 2002, "value": 23756 },
      { "year": 2003, "value": 22148 },
      { "year": 2004, "value": 19378 },
      { "year": 2005, "value": 22715 },
      { "year": 2006, "value": 25302 },
      { "year": 2007, "value": 24274 },
      { "year": 2008, "value": 23070 },
      { "year": 2009, "value": 25646 },
      { "year": 2010, "value": 21380 },
      { "year": 2011, "value": 21726 },
      { "year": 2012, "value": 21341 },
      { "year": 2013, "value": 22153 },
      { "year": 2014, "value": 15509 },
      { "year": 2015, "value": 12353 },
      { "year": 2016, "value": 14560 }
    ],
    "annotations": []
  }, {
    "id": "abschiebungen",
    "unit": "Tsd.",
    "factor": 1000,
    "max": 50000,
    "precision": 10,
    "breakpoint": 2005,
    "values": [
      { "year": 2002, "value": 29036 },
      { "year": 2003, "value": 26487 },
      { "year": 2004, "value": 23334 },
      { "year": 2005, "value": 17773 },
      { "year": 2006, "value": 13894 },
      { "year": 2007, "value": 9617 },
      { "year": 2008, "value": 8394 },
      { "year": 2009, "value": 7830 },
      { "year": 2010, "value": 7558 },
      { "year": 2011, "value": 7917 },
      { "year": 2012, "value": 7651 },
      { "year": 2013, "value": 10198 },
      { "year": 2014, "value": 10884 },
      { "year": 2015, "value": 20888 },
      { "year": 2016, "value": 25375 }
    ],
    "annotations": []
  }, {
    "id": "kernkraftwerke",
    "unit": "",
    "factor": 1,
    "max": 30,
    "precision": 1,
    "breakpoint": 2005,
    "values": [
      { "year": 2002, "value": 19 },
      { "year": 2003, "value": 19 },
      { "year": 2004, "value": 18 },
      { "year": 2005, "value": 18 },
      { "year": 2006, "value": 17 },
      { "year": 2007, "value": 17 },
      { "year": 2008, "value": 17 },
      { "year": 2009, "value": 17 },
      { "year": 2010, "value": 17 },
      { "year": 2011, "value": 17 },
      { "year": 2012, "value": 9 },
      { "year": 2013, "value": 9 },
      { "year": 2014, "value": 9 },
      { "year": 2015, "value": 9 },
      { "year": 2016, "value": 8 }
    ],
    "annotations": [
    {
        "text": "Fukushima",
        "color": "#000",
        "year": 2011,
        "value": 17
      }
    ]
  }, {
    "id": "betreuungsquote",
    "unit": "%",
    "factor": 1,
    "max": 40,
    "precision": 10,
    "breakpoint": 2005,
    "values": [
      { "year": 2002, "value": 10.2 },
      { "year": 2003, "value": 10.4 },
      { "year": 2006, "value": 13.6 },
      { "year": 2007, "value": 15.5 },
      { "year": 2008, "value": 17.6 },
      { "year": 2009, "value": 20.2 },
      { "year": 2010, "value": 23 },
      { "year": 2011, "value": 25.2 },
      { "year": 2012, "value": 27.6 },
      { "year": 2013, "value": 29.3 },
      { "year": 2014, "value": 32.3 },
      { "year": 2015, "value": 32.9 },
      { "year": 2016, "value": 32.7 }
    ],
    "annotations": [
      {
        "text": "Rechtsanspruch auf Kitaplatz",
        "color": "#000",
        "year": 2013,
        "value": 29.3
      },{
        "text": "keine Daten",
        "color": "#000",
        "year": 2004.5,
        "value": 11
      }
    ]
  }, {
    "id": "co2",
    "unit": "Mio. T",
    "factor": 1000,
    "max": 1300000,
    "precision": 10,
    "breakpoint": 2005,
    "values": [
      { "year": 2002, "value": 1036925 },
      { "year": 2003, "value": 1033843 },
      { "year": 2004, "value": 1017276 },
      { "year": 2005, "value": 991933 },
      { "year": 2006, "value": 999220 },
      { "year": 2007, "value": 972344 },
      { "year": 2008, "value": 974682 },
      { "year": 2009, "value": 906949 },
      { "year": 2010, "value": 941750 },
      { "year": 2011, "value": 922363 },
      { "year": 2012, "value": 926850 },
      { "year": 2013, "value": 945186 },
      { "year": 2014, "value": 904262 },
      { "year": 2015, "value": 901932 }
    ],
    "annotations": []
  }, {
    "id": "exporte",
    "unit": "Bio. €",
    "factor": 1000000,
    "max": 1300000,
    "precision": 10,
    "breakpoint": 2005,
    "values": [
      { "year": 2002, "value": 651320 },
      { "year": 2003, "value": 664455 },
      { "year": 2004, "value": 731544 },
      { "year": 2005, "value": 786266 },
      { "year": 2006, "value": 893042 },
      { "year": 2007, "value": 965236 },
      { "year": 2008, "value": 984140 },
      { "year": 2009, "value": 803312 },
      { "year": 2010, "value": 951959 },
      { "year": 2011, "value": 1061225 },
      { "year": 2012, "value": 1092627 },
      { "year": 2013, "value": 1088025 },
      { "year": 2014, "value": 1123746 },
      { "year": 2015, "value": 1193555 }
    ],
    "annotations": [
      {
        "text": "Wirtschaftskrise",
        "color": "#000",
        "year": 2009,
        "value": 803312
      }
    ]
  }
]
